pious/__init__.py
pious/__main__.py
pious/_hand_table.py
pious/conf.py
pious/flops.py
pious/hand_categories.py
pious/hands.py
pious/progress_bar.py
pious/range.py
pious/util.py
pious/_executables/__init__.py
pious/_executables/aggregate.py
pious/_executables/aggregation_viewer.py
pious/_executables/blockers.py
pious/_executables/conf.py
pious/_executables/flops.py
pious/_executables/lines.py
pious/_executables/version.py
pious/hrc/__init__.py
pious/hrc/game_state.py
pious/hrc/hand.py
pious/hrc/trainer.py
pious/hrc/resources/__init__.py
pious/hrc/resources/sims/__init__.py
pious/hrc/resources/sims/2.5_rfi/settings.json
pious/hrc/resources/sims/2.5_rfi/nodes/0.json
pious/hrc/resources/sims/2.5_rfi/nodes/1.json
pious/hrc/resources/sims/2.5_rfi/nodes/10.json
pious/hrc/resources/sims/2.5_rfi/nodes/100.json
pious/hrc/resources/sims/2.5_rfi/nodes/101.json
pious/hrc/resources/sims/2.5_rfi/nodes/102.json
pious/hrc/resources/sims/2.5_rfi/nodes/103.json
pious/hrc/resources/sims/2.5_rfi/nodes/104.json
pious/hrc/resources/sims/2.5_rfi/nodes/105.json
pious/hrc/resources/sims/2.5_rfi/nodes/106.json
pious/hrc/resources/sims/2.5_rfi/nodes/107.json
pious/hrc/resources/sims/2.5_rfi/nodes/108.json
pious/hrc/resources/sims/2.5_rfi/nodes/109.json
pious/hrc/resources/sims/2.5_rfi/nodes/11.json
pious/hrc/resources/sims/2.5_rfi/nodes/110.json
pious/hrc/resources/sims/2.5_rfi/nodes/111.json
pious/hrc/resources/sims/2.5_rfi/nodes/112.json
pious/hrc/resources/sims/2.5_rfi/nodes/113.json
pious/hrc/resources/sims/2.5_rfi/nodes/114.json
pious/hrc/resources/sims/2.5_rfi/nodes/115.json
pious/hrc/resources/sims/2.5_rfi/nodes/116.json
pious/hrc/resources/sims/2.5_rfi/nodes/117.json
pious/hrc/resources/sims/2.5_rfi/nodes/118.json
pious/hrc/resources/sims/2.5_rfi/nodes/119.json
pious/hrc/resources/sims/2.5_rfi/nodes/12.json
pious/hrc/resources/sims/2.5_rfi/nodes/120.json
pious/hrc/resources/sims/2.5_rfi/nodes/121.json
pious/hrc/resources/sims/2.5_rfi/nodes/122.json
pious-0.0.1.dist-info/METADATA
pious-0.0.1.dist-info/WHEEL
pious-0.0.1.dist-info/entry_points.txt
pious-0.0.1.dist-info/licenses/LICENSE
pious-0.0.1.dist-info/RECORD
