Metadata-Version: 2.4
Name: pious
Version: 0.0.1
Summary: The PioSOLVER Utility Suite
Project-URL: Issues, https://github.com/bkushigian/Pious/issues
Project-URL: Homepage, https://github.com/bkushigian/Pious
Author-email: Ben Kushigian <bkushigian@gmail.com>
License-File: LICENSE
Classifier: License :: OSI Approved :: MIT License
Classifier: Operating System :: OS Independent
Classifier: Programming Language :: Python :: 3
Requires-Python: >=3.11
Requires-Dist: ansi>=0.3.7
Requires-Dist: matplotlib>=3.7.1
Requires-Dist: mplcursors>=0.5.1
Requires-Dist: numpy>=2.0.0
Requires-Dist: pandas>=2.0.3
Requires-Dist: pytest>=8.2.2
Requires-Dist: tabulate>=0.9.0
